thiscn/__init__.py
thiscn-0.0.1.dist-info/METADATA
thiscn-0.0.1.dist-info/RECORD
thiscn-0.0.1.dist-info/WHEEL
thiscn-0.0.1.dist-info/top_level.txt
